odoo/addons/helpdesk_cc_and_to_text/README.rst
odoo/addons/helpdesk_cc_and_to_text/__init__.py
odoo/addons/helpdesk_cc_and_to_text/__manifest__.py
odoo/addons/helpdesk_cc_and_to_text/i18n/ca_ES.po
odoo/addons/helpdesk_cc_and_to_text/i18n/en_US.po
odoo/addons/helpdesk_cc_and_to_text/i18n/es.po
odoo/addons/helpdesk_cc_and_to_text/models/__init__.py
odoo/addons/helpdesk_cc_and_to_text/models/helpdesk_ticket.py
odoo/addons/helpdesk_cc_and_to_text/static/description/icon.png
odoo/addons/helpdesk_cc_and_to_text/tests/__init__.py
odoo/addons/helpdesk_cc_and_to_text/tests/test_helpdesk_ticket.py
odoo/addons/helpdesk_cc_and_to_text/views/helpdesk_ticket_view.xml
odoo12_addon_helpdesk_cc_and_to_text-12.0.0.1.1.dist-info/METADATA
odoo12_addon_helpdesk_cc_and_to_text-12.0.0.1.1.dist-info/WHEEL
odoo12_addon_helpdesk_cc_and_to_text-12.0.0.1.1.dist-info/top_level.txt
odoo12_addon_helpdesk_cc_and_to_text-12.0.0.1.1.dist-info/RECORD
